regexlint/__init__.py
regexlint/bitvector.py
regexlint/charclass.py
regexlint/checkers.py
regexlint/cmdline.py
regexlint/indicator.py
regexlint/indicator_ast.py
regexlint/indicator_pyg.py
regexlint/indicator_substr.py
regexlint/parser.py
regexlint/util.py
regexlint-2.0.dist-info/COPYING
regexlint-2.0.dist-info/METADATA
regexlint-2.0.dist-info/WHEEL
regexlint-2.0.dist-info/entry_points.txt
regexlint-2.0.dist-info/top_level.txt
regexlint-2.0.dist-info/RECORD
