Metadata-Version: 2.1
Name: regexlint
Version: 2.0
Summary: Linter for (Pygments) regular expressions
Home-page: https://github.com/thatch/regexlint/
Author: Tim Hatch
Author-email: tim@timhatch.com
License: Apache
Platform: UNKNOWN
Classifier: License :: OSI Approved :: Apache Software License
Classifier: Intended Audience :: Developers
Classifier: Development Status :: 5 - Production/Stable
Classifier: Operating System :: OS Independent
Classifier: Topic :: Software Development :: Quality Assurance
Classifier: Programming Language :: Python :: 3.6
Classifier: Programming Language :: Python :: 3.7
Classifier: Programming Language :: Python :: 3.8
Requires-Python: >=3.6
Requires-Dist: Pygments
